youtube_snoop/__init__.py
youtube_snoop/__main__.py
youtube_snoop/cli.py
youtube_snoop/coverart.py
youtube_snoop/downloader.py
youtube_snoop/metadata.py
youtube_snoop/parser.py
youtube_snoop/utils.py
youtubesnoop-0.1.6.dist-info/METADATA
youtubesnoop-0.1.6.dist-info/WHEEL
youtubesnoop-0.1.6.dist-info/entry_points.txt
youtubesnoop-0.1.6.dist-info/licenses/LICENSE
youtubesnoop-0.1.6.dist-info/RECORD
