Metadata-Version: 2.4
Name: youtubesnoop
Version: 0.1.6
Summary: YouTube video/music downloader with metadata tagging and cover art
Project-URL: Homepage, https://github.com/anderslatif/YoutubeSnoop
Project-URL: Repository, https://github.com/anderslatif/YoutubeSnoop
Project-URL: Issues, https://github.com/anderslatif/YoutubeSnoop/issues
Author: Anders
License: MIT
License-File: LICENSE
Keywords: downloader,flac,metadata,music,musicbrainz,youtube
Classifier: Development Status :: 3 - Alpha
Classifier: Intended Audience :: End Users/Desktop
Classifier: Programming Language :: Python :: 3
Classifier: Programming Language :: Python :: 3.8
Classifier: Programming Language :: Python :: 3.9
Classifier: Programming Language :: Python :: 3.10
Classifier: Programming Language :: Python :: 3.11
Classifier: Programming Language :: Python :: 3.12
Classifier: Programming Language :: Python :: 3.13
Classifier: Programming Language :: Python :: 3.14
Requires-Python: >=3.8
Requires-Dist: click>=8.0.0
Requires-Dist: filetype>=1.2.0
Requires-Dist: musicbrainzngs>=0.7.1
Requires-Dist: mutagen>=1.47.0
Requires-Dist: questionary>=2.0.0
Requires-Dist: requests>=2.31.0
Requires-Dist: yt-dlp
